ligavision/dsl/__init__.py
ligavision/dsl/__version__.py
ligavision/dsl/base.py
ligavision/dsl/conf.py
ligavision/dsl/geometry.py
ligavision/dsl/mixin.py
ligavision/dsl/rle.py
ligavision/dsl/text.py
ligavision/dsl/video.py
ligavision/dsl/vision.py
ligavision_dsl-0.2.0.dist-info/METADATA
ligavision_dsl-0.2.0.dist-info/WHEEL
ligavision_dsl-0.2.0.dist-info/namespace_packages.txt
ligavision_dsl-0.2.0.dist-info/top_level.txt
ligavision_dsl-0.2.0.dist-info/RECORD
