Metadata-Version: 2.1
Name: ligavision-dsl
Version: 0.2.0
Requires-Python: <3.10,>=3.8
Requires-Dist: Pillow
Requires-Dist: aiohttp
Requires-Dist: fsspec
Requires-Dist: numpy
Requires-Dist: requests
